torch_mfcc/__init__.py
torch_mfcc/conv_stft.py
torch_mfcc/torch_fbank.py
torch_mfcc/torch_mfcc.py
torch_mfcc-0.2.0.dist-info/LICENSE
torch_mfcc-0.2.0.dist-info/METADATA
torch_mfcc-0.2.0.dist-info/WHEEL
torch_mfcc-0.2.0.dist-info/top_level.txt
torch_mfcc-0.2.0.dist-info/RECORD
