Metadata-Version: 2.1
Name: torch-mfcc
Version: 0.2.0
Summary: A librosa's STFT/FBANK/MFCC implement based on Torch
Home-page: https://github.com/echocatzh/torch-mfcc
Author: Shimin Zhang
Author-email: shmzhang@npu-aslp.org
License: MIT
Platform: UNKNOWN
Requires-Dist: numpy
Requires-Dist: scipy
Requires-Dist: librosa
